tensorrt_dispatch/__init__.py
tensorrt_dispatch/libnvinfer_dispatch.so.8
tensorrt_dispatch/tensorrt_dispatch.so
tensorrt_dispatch-8.6.0.dist-info/LICENSE.txt
tensorrt_dispatch-8.6.0.dist-info/METADATA
tensorrt_dispatch-8.6.0.dist-info/WHEEL
tensorrt_dispatch-8.6.0.dist-info/top_level.txt
tensorrt_dispatch-8.6.0.dist-info/zip-safe
tensorrt_dispatch-8.6.0.dist-info/RECORD
